[
    {
        "featureType": "all",
        "elementType": "all",
        "stylers": [
            {
                "saturation": "0"
            },
            {
                "color": "#58106e"
            }
        ]
    },
    {
        "featureType": "administrative",
        "elementType": "all",
        "stylers": [
            {
                "visibility": "simplified"
            }
        ]
    },
    {
        "featureType": "administrative",
        "elementType": "labels.text.fill",
        "stylers": [
            {
                "color": "#e8b8f9"
            }
        ]
    },
    {
        "featureType": "administrative.country",
        "elementType": "geometry.stroke",
        "stylers": [
            {
                "color": "#743677"
            },
            {
                "visibility": "on"
            }
        ]
    },
    {
        "featureType": "administrative.province",
        "elementType": "geometry.stroke",
        "stylers": [
            {
                "visibility": "on"
            },
            {
                "color": "#934a9f"
            }
        ]
    },
    {
        "featureType": "landscape",
        "elementType": "all",
        "stylers": [
            {
                "color": "#58106e"
            },
            {
                "visibility": "simplified"
            }
        ]
    },
    {
        "featureType": "landscape.natural",
        "elementType": "all",
        "stylers": [
            {
                "visibility": "simplified"
            },
            {
                "color": "#5a0a76"
            }
        ]
    },
    {
        "featureType": "landscape.natural.landcover",
        "elementType": "all",
        "stylers": [
            {
                "visibility": "simplified"
            },
            {
                "color": "#58176e"
            }
        ]
    },
    {
        "featureType": "poi",
        "elementType": "all",
        "stylers": [
            {
                "visibility": "off"
            }
        ]
    },
    {
        "featureType": "road",
        "elementType": "geometry",
        "stylers": [
            {
                "color": "#a02aca"
            }
        ]
    },
    {
        "featureType": "road.highway",
        "elementType": "geometry",
        "stylers": [
            {
                "visibility": "simplified"
            },
            {
                "color": "#550d6f"
            }
        ]
    },
    {
        "featureType": "road.highway",
        "elementType": "labels",
        "stylers": [
            {
                "visibility": "off"
            }
        ]
    },
    {
        "featureType": "road.highway.controlled_access",
        "elementType": "labels",
        "stylers": [
            {
                "visibility": "off"
            }
        ]
    },
    {
        "featureType": "road.arterial",
        "elementType": "geometry",
        "stylers": [
            {
                "visibility": "off"
            }
        ]
    },
    {
        "featureType": "road.arterial",
        "elementType": "labels.icon",
        "stylers": [
            {
                "visibility": "off"
            }
        ]
    },
    {
        "featureType": "road.local",
        "elementType": "labels",
        "stylers": [
            {
                "visibility": "off"
            }
        ]
    },
    {
        "featureType": "water",
        "elementType": "all",
        "stylers": [
            {
                "color": "#ffffff"
            },
            {
                "visibility": "on"
            }
        ]
    },
    {
        "featureType": "water",
        "elementType": "geometry",
        "stylers": [
            {
                "color": "#fafafa"
            }
        ]
    },
    {
        "featureType": "water",
        "elementType": "labels",
        "stylers": [
            {
                "visibility": "simplified"
            },
            {
                "color": "#a02aca"
            }
        ]
    }
]